lawsql_utils/__init__.py
lawsql_utils/files/__init__.py
lawsql_utils/files/load_tree_files.py
lawsql_utils/files/path_to_local.py
lawsql_utils/general/__init__.py
lawsql_utils/general/combine_iterators.py
lawsql_utils/general/patterns.py
lawsql_utils/general/regex_constructors.py
lawsql_utils/general/text_helpers.py
lawsql_utils/html/__init__.py
lawsql_utils/html/containerization.py
lawsql_utils/html/footnotes.py
lawsql_utils/html/formatting.py
lawsql_utils/trees/__init__.py
lawsql_utils/trees/case_events.py
lawsql_utils/trees/clear_nested.py
lawsql_utils/trees/create_nested.py
lawsql_utils/trees/identities.py
lawsql_utils/trees/statutory_events.py
lawsql_utils/trees/validate_dict_list_dict.py
lawsql_utils/trees/values_from_walk_tree.py
lawsql_utils-0.0.3.dist-info/WHEEL
lawsql_utils-0.0.3.dist-info/METADATA
lawsql_utils-0.0.3.dist-info/RECORD
