Metadata-Version: 2.1
Name: lawsql-utils
Version: 0.0.3
Summary: lawsql helper functions
Author: Marcelino G. Veloso III
Author-email: mars@veloso.one
Requires-Python: >=3.9,<4.0
Classifier: Programming Language :: Python :: 3
Classifier: Programming Language :: Python :: 3.9
Classifier: Programming Language :: Python :: 3.10
Requires-Dist: PyYAML (>=6.0,<7.0)
Requires-Dist: arrow (>=1.2,<2.0)
Requires-Dist: beautifulsoup4 (>=4.10.0,<5.0.0)
Requires-Dist: html5lib (>=1.1,<2.0)
Requires-Dist: markdown2 (>=2.4.0,<3.0.0)
Requires-Dist: python-dateutil (>=2.8.2,<3.0.0)
Requires-Dist: python-dotenv (>=0.19.2,<0.20.0)
Requires-Dist: types-PyYAML (>=6.0,<7.0)
Requires-Dist: types-python-dateutil (>=2.8.0,<3.0.0)
